{
  "savedAt": "2026-04-28T00:04:49.414Z",
  "payload": {
    "fetchedAt": "2026-04-28T00:04:49.344Z",
    "source": "massive",
    "ticker": "SATA",
    "fullName": "Strive Variable Rate Series A Perpetual Preferred",
    "exchange": "NasdaqGM",
    "firstTradeDate": "2025-11-10",
    "parFloor": 100,
    "dataAvailability": {
      "daily": true,
      "fiveMin": true,
      "oneMin": true,
      "intraday": true
    },
    "current": {
      "price": 99.99,
      "volume": 157621.980313,
      "dayHigh": 100,
      "dayLow": 99.92,
      "fiftyTwoWeekHigh": 100.53,
      "fiftyTwoWeekLow": 82.5,
      "lastDate": "2026-04-27",
      "lastMinuteTs": 1777329780
    },
    "disclosures": [
      {
        "date": "2025-11-10",
        "event": "IPO",
        "shares": 2000000,
        "price": 80,
        "type": "ipo",
        "grossProceeds": 160000000,
        "note": "Initial public offering of SATA (upsized & oversubscribed)"
      },
      {
        "date": "2026-01-28",
        "event": "Follow-on offering",
        "shares": 1320000,
        "price": 90,
        "type": "followon",
        "grossProceeds": 118800000,
        "note": "Registered follow-on. Priced below par ($90) — not via ATM."
      },
      {
        "date": "2026-04-02",
        "event": "Total SATA outstanding",
        "sharesOutstanding": 4373194,
        "type": "outstanding",
        "note": "Implies ~1,053,194 shares issued via ATM between Dec 2025 and Apr 2, 2026"
      },
      {
        "date": "2026-04-22",
        "event": "After-hours session",
        "shares": 100000,
        "price": 100,
        "type": "ah_session",
        "source": "Matt Cole (Strive CEO) on X",
        "note": "100,000 shares traded after-hours at $100 par (per Matt Cole X post)"
      },
      {
        "date": "2026-04-23",
        "event": "After-hours session",
        "shares": 100000,
        "price": 100,
        "type": "ah_session",
        "source": "Matt Cole (Strive CEO) on X",
        "note": "100,000 shares traded after-hours at $100 par (per Matt Cole X post)"
      }
    ],
    "rows": [
      {
        "date": "2025-11-10",
        "open": 91,
        "high": 93.89,
        "low": 89.66,
        "close": 92.15,
        "volume": 492864,
        "qualifyingShares": null,
        "qualifyingDollarVolume": null,
        "qualifyingAvgPrice": null,
        "qualifyingSource": null
      },
      {
        "date": "2025-11-11",
        "open": 92.99,
        "high": 93,
        "low": 91.7,
        "close": 92.48,
        "volume": 357880,
        "qualifyingShares": null,
        "qualifyingDollarVolume": null,
        "qualifyingAvgPrice": null,
        "qualifyingSource": null
      },
      {
        "date": "2025-11-12",
        "open": 93.79,
        "high": 96,
        "low": 93.01,
        "close": 95.4499,
        "volume": 445565,
        "qualifyingShares": null,
        "qualifyingDollarVolume": null,
        "qualifyingAvgPrice": null,
        "qualifyingSource": null
      },
      {
        "date": "2025-11-13",
        "open": 96,
        "high": 98.7175,
        "low": 95.43,
        "close": 96,
        "volume": 246286,
        "qualifyingShares": null,
        "qualifyingDollarVolume": null,
        "qualifyingAvgPrice": null,
        "qualifyingSource": null
      },
      {
        "date": "2025-11-14",
        "open": 95,
        "high": 95.49,
        "low": 94,
        "close": 95.1,
        "volume": 133131,
        "qualifyingShares": null,
        "qualifyingDollarVolume": null,
        "qualifyingAvgPrice": null,
        "qualifyingSource": null
      },
      {
        "date": "2025-11-17",
        "open": 95.97,
        "high": 95.97,
        "low": 90,
        "close": 91.29,
        "volume": 213374,
        "qualifyingShares": null,
        "qualifyingDollarVolume": null,
        "qualifyingAvgPrice": null,
        "qualifyingSource": null
      },
      {
        "date": "2025-11-18",
        "open": 90.03,
        "high": 94,
        "low": 89.7,
        "close": 92.88,
        "volume": 134519,
        "qualifyingShares": null,
        "qualifyingDollarVolume": null,
        "qualifyingAvgPrice": null,
        "qualifyingSource": null
      },
      {
        "date": "2025-11-19",
        "open": 93.75,
        "high": 93.848,
        "low": 88.5,
        "close": 89.02,
        "volume": 215730,
        "qualifyingShares": null,
        "qualifyingDollarVolume": null,
        "qualifyingAvgPrice": null,
        "qualifyingSource": null
      },
      {
        "date": "2025-11-20",
        "open": 89.9,
        "high": 91.258,
        "low": 86.0901,
        "close": 87.5,
        "volume": 84365,
        "qualifyingShares": null,
        "qualifyingDollarVolume": null,
        "qualifyingAvgPrice": null,
        "qualifyingSource": null
      },
      {
        "date": "2025-11-21",
        "open": 87.5,
        "high": 91.2799,
        "low": 85.5001,
        "close": 90.8,
        "volume": 100542,
        "qualifyingShares": null,
        "qualifyingDollarVolume": null,
        "qualifyingAvgPrice": null,
        "qualifyingSource": null
      },
      {
        "date": "2025-11-24",
        "open": 92.55,
        "high": 92.74,
        "low": 91.5,
        "close": 91.98,
        "volume": 61896,
        "qualifyingShares": null,
        "qualifyingDollarVolume": null,
        "qualifyingAvgPrice": null,
        "qualifyingSource": null
      },
      {
        "date": "2025-11-25",
        "open": 92.95,
        "high": 92.95,
        "low": 90.955,
        "close": 91.2,
        "volume": 37218,
        "qualifyingShares": null,
        "qualifyingDollarVolume": null,
        "qualifyingAvgPrice": null,
        "qualifyingSource": null
      },
      {
        "date": "2025-11-26",
        "open": 91.9,
        "high": 92.75,
        "low": 91.25,
        "close": 91.72,
        "volume": 54275,
        "qualifyingShares": null,
        "qualifyingDollarVolume": null,
        "qualifyingAvgPrice": null,
        "qualifyingSource": null
      },
      {
        "date": "2025-11-28",
        "open": 92.95,
        "high": 94.595,
        "low": 92.81,
        "close": 93.71,
        "volume": 64340,
        "qualifyingShares": null,
        "qualifyingDollarVolume": null,
        "qualifyingAvgPrice": null,
        "qualifyingSource": null
      },
      {
        "date": "2025-12-01",
        "open": 92.37,
        "high": 92.37,
        "low": 90.82,
        "close": 91.6547,
        "volume": 49316,
        "qualifyingShares": null,
        "qualifyingDollarVolume": null,
        "qualifyingAvgPrice": null,
        "qualifyingSource": null
      },
      {
        "date": "2025-12-02",
        "open": 91.8,
        "high": 92.2399,
        "low": 91.61,
        "close": 91.89,
        "volume": 103640,
        "qualifyingShares": null,
        "qualifyingDollarVolume": null,
        "qualifyingAvgPrice": null,
        "qualifyingSource": null
      },
      {
        "date": "2025-12-03",
        "open": 92.46,
        "high": 92.5,
        "low": 91.1001,
        "close": 91.76,
        "volume": 43983,
        "qualifyingShares": null,
        "qualifyingDollarVolume": null,
        "qualifyingAvgPrice": null,
        "qualifyingSource": null
      },
      {
        "date": "2025-12-04",
        "open": 92.13,
        "high": 92.13,
        "low": 91.51,
        "close": 91.61,
        "volume": 23551,
        "qualifyingShares": null,
        "qualifyingDollarVolume": null,
        "qualifyingAvgPrice": null,
        "qualifyingSource": null
      },
      {
        "date": "2025-12-05",
        "open": 91.76,
        "high": 92.24,
        "low": 90.57,
        "close": 91.65,
        "volume": 18700,
        "qualifyingShares": null,
        "qualifyingDollarVolume": null,
        "qualifyingAvgPrice": null,
        "qualifyingSource": null
      },
      {
        "date": "2025-12-08",
        "open": 92,
        "high": 92.4,
        "low": 91.01,
        "close": 91.07,
        "volume": 50523,
        "qualifyingShares": null,
        "qualifyingDollarVolume": null,
        "qualifyingAvgPrice": null,
        "qualifyingSource": null
      },
      {
        "date": "2025-12-09",
        "open": 91.75,
        "high": 91.75,
        "low": 91.03,
        "close": 91.15,
        "volume": 60069,
        "qualifyingShares": null,
        "qualifyingDollarVolume": null,
        "qualifyingAvgPrice": null,
        "qualifyingSource": null
      },
      {
        "date": "2025-12-10",
        "open": 91.55,
        "high": 91.55,
        "low": 90.19,
        "close": 90.2,
        "volume": 69216,
        "qualifyingShares": null,
        "qualifyingDollarVolume": null,
        "qualifyingAvgPrice": null,
        "qualifyingSource": null
      },
      {
        "date": "2025-12-11",
        "open": 90.99,
        "high": 91.8,
        "low": 90.99,
        "close": 91.59,
        "volume": 14532,
        "qualifyingShares": null,
        "qualifyingDollarVolume": null,
        "qualifyingAvgPrice": null,
        "qualifyingSource": null
      },
      {
        "date": "2025-12-12",
        "open": 91.77,
        "high": 91.9,
        "low": 90.602,
        "close": 91.02,
        "volume": 26563,
        "qualifyingShares": null,
        "qualifyingDollarVolume": null,
        "qualifyingAvgPrice": null,
        "qualifyingSource": null
      },
      {
        "date": "2025-12-15",
        "open": 91.77,
        "high": 91.77,
        "low": 90.21,
        "close": 90.22,
        "volume": 43908,
        "qualifyingShares": null,
        "qualifyingDollarVolume": null,
        "qualifyingAvgPrice": null,
        "qualifyingSource": null
      },
      {
        "date": "2025-12-16",
        "open": 91,
        "high": 92,
        "low": 90.63,
        "close": 91.51,
        "volume": 73591,
        "qualifyingShares": null,
        "qualifyingDollarVolume": null,
        "qualifyingAvgPrice": null,
        "qualifyingSource": null
      },
      {
        "date": "2025-12-17",
        "open": 91.6,
        "high": 92.5,
        "low": 90.51,
        "close": 91.25,
        "volume": 77446,
        "qualifyingShares": null,
        "qualifyingDollarVolume": null,
        "qualifyingAvgPrice": null,
        "qualifyingSource": null
      },
      {
        "date": "2025-12-18",
        "open": 92.06,
        "high": 92.24,
        "low": 91.6,
        "close": 92.23,
        "volume": 34987,
        "qualifyingShares": null,
        "qualifyingDollarVolume": null,
        "qualifyingAvgPrice": null,
        "qualifyingSource": null
      },
      {
        "date": "2025-12-19",
        "open": 91.7,
        "high": 93.552,
        "low": 91.7,
        "close": 92.97,
        "volume": 49199,
        "qualifyingShares": null,
        "qualifyingDollarVolume": null,
        "qualifyingAvgPrice": null,
        "qualifyingSource": null
      },
      {
        "date": "2025-12-22",
        "open": 93.35,
        "high": 93.81,
        "low": 92.9801,
        "close": 93.75,
        "volume": 67669,
        "qualifyingShares": null,
        "qualifyingDollarVolume": null,
        "qualifyingAvgPrice": null,
        "qualifyingSource": null
      },
      {
        "date": "2025-12-23",
        "open": 93.77,
        "high": 95,
        "low": 93.6601,
        "close": 94.9,
        "volume": 33325,
        "qualifyingShares": null,
        "qualifyingDollarVolume": null,
        "qualifyingAvgPrice": null,
        "qualifyingSource": null
      },
      {
        "date": "2025-12-24",
        "open": 94.9,
        "high": 95,
        "low": 94.5915,
        "close": 94.9,
        "volume": 23243,
        "qualifyingShares": null,
        "qualifyingDollarVolume": null,
        "qualifyingAvgPrice": null,
        "qualifyingSource": null
      },
      {
        "date": "2025-12-26",
        "open": 94.9,
        "high": 94.9,
        "low": 94.5,
        "close": 94.83,
        "volume": 45811,
        "qualifyingShares": null,
        "qualifyingDollarVolume": null,
        "qualifyingAvgPrice": null,
        "qualifyingSource": null
      },
      {
        "date": "2025-12-29",
        "open": 94.89,
        "high": 94.9,
        "low": 94.764,
        "close": 94.85,
        "volume": 47781,
        "qualifyingShares": null,
        "qualifyingDollarVolume": null,
        "qualifyingAvgPrice": null,
        "qualifyingSource": null
      },
      {
        "date": "2025-12-30",
        "open": 95.25,
        "high": 95.3,
        "low": 94.78,
        "close": 95,
        "volume": 88848,
        "qualifyingShares": null,
        "qualifyingDollarVolume": null,
        "qualifyingAvgPrice": null,
        "qualifyingSource": null
      },
      {
        "date": "2025-12-31",
        "open": 93.81,
        "high": 95.24,
        "low": 93.81,
        "close": 95.09,
        "volume": 286091,
        "qualifyingShares": null,
        "qualifyingDollarVolume": null,
        "qualifyingAvgPrice": null,
        "qualifyingSource": null
      },
      {
        "date": "2026-01-02",
        "open": 94.4,
        "high": 94.75,
        "low": 93.1401,
        "close": 94.0878,
        "volume": 47365,
        "qualifyingShares": null,
        "qualifyingDollarVolume": null,
        "qualifyingAvgPrice": null,
        "qualifyingSource": null
      },
      {
        "date": "2026-01-05",
        "open": 94.1,
        "high": 94.8,
        "low": 93.83,
        "close": 94.25,
        "volume": 76759,
        "qualifyingShares": null,
        "qualifyingDollarVolume": null,
        "qualifyingAvgPrice": null,
        "qualifyingSource": null
      },
      {
        "date": "2026-01-06",
        "open": 94.25,
        "high": 95.11,
        "low": 94.2,
        "close": 95,
        "volume": 37260,
        "qualifyingShares": null,
        "qualifyingDollarVolume": null,
        "qualifyingAvgPrice": null,
        "qualifyingSource": null
      },
      {
        "date": "2026-01-07",
        "open": 95,
        "high": 95.75,
        "low": 95,
        "close": 95.35,
        "volume": 48670,
        "qualifyingShares": null,
        "qualifyingDollarVolume": null,
        "qualifyingAvgPrice": null,
        "qualifyingSource": null
      },
      {
        "date": "2026-01-08",
        "open": 95.34,
        "high": 95.75,
        "low": 94.99,
        "close": 95.55,
        "volume": 25040,
        "qualifyingShares": null,
        "qualifyingDollarVolume": null,
        "qualifyingAvgPrice": null,
        "qualifyingSource": null
      },
      {
        "date": "2026-01-09",
        "open": 95.375,
        "high": 97.96,
        "low": 95.375,
        "close": 97.1,
        "volume": 109682,
        "qualifyingShares": null,
        "qualifyingDollarVolume": null,
        "qualifyingAvgPrice": null,
        "qualifyingSource": null
      },
      {
        "date": "2026-01-12",
        "open": 95,
        "high": 97.1,
        "low": 95,
        "close": 97,
        "volume": 45904,
        "qualifyingShares": null,
        "qualifyingDollarVolume": null,
        "qualifyingAvgPrice": null,
        "qualifyingSource": null
      },
      {
        "date": "2026-01-13",
        "open": 95.92,
        "high": 97.2,
        "low": 95.92,
        "close": 96.97,
        "volume": 42556,
        "qualifyingShares": null,
        "qualifyingDollarVolume": null,
        "qualifyingAvgPrice": null,
        "qualifyingSource": null
      },
      {
        "date": "2026-01-14",
        "open": 97.25,
        "high": 98.04,
        "low": 96.52,
        "close": 98.04,
        "volume": 36546,
        "qualifyingShares": null,
        "qualifyingDollarVolume": null,
        "qualifyingAvgPrice": null,
        "qualifyingSource": null
      },
      {
        "date": "2026-01-15",
        "open": 98,
        "high": 98,
        "low": 97.9,
        "close": 98,
        "volume": 76408,
        "qualifyingShares": null,
        "qualifyingDollarVolume": null,
        "qualifyingAvgPrice": null,
        "qualifyingSource": null
      },
      {
        "date": "2026-01-16",
        "open": 98.25,
        "high": 101.35,
        "low": 97.91,
        "close": 100.53,
        "volume": 103554,
        "qualifyingShares": null,
        "qualifyingDollarVolume": null,
        "qualifyingAvgPrice": null,
        "qualifyingSource": null
      },
      {
        "date": "2026-01-20",
        "open": 100.48,
        "high": 100.48,
        "low": 98.52,
        "close": 99.9,
        "volume": 168489,
        "qualifyingShares": null,
        "qualifyingDollarVolume": null,
        "qualifyingAvgPrice": null,
        "qualifyingSource": null
      },
      {
        "date": "2026-01-21",
        "open": 100,
        "high": 100.44,
        "low": 99.5,
        "close": 99.5,
        "volume": 122632,
        "qualifyingShares": null,
        "qualifyingDollarVolume": null,
        "qualifyingAvgPrice": null,
        "qualifyingSource": null
      },
      {
        "date": "2026-01-22",
        "open": 97,
        "high": 97.075,
        "low": 94,
        "close": 95.27,
        "volume": 987206,
        "qualifyingShares": null,
        "qualifyingDollarVolume": null,
        "qualifyingAvgPrice": null,
        "qualifyingSource": null
      },
      {
        "date": "2026-01-23",
        "open": 95.5,
        "high": 96.71,
        "low": 95.4255,
        "close": 96.35,
        "volume": 198239,
        "qualifyingShares": null,
        "qualifyingDollarVolume": null,
        "qualifyingAvgPrice": null,
        "qualifyingSource": null
      },
      {
        "date": "2026-01-26",
        "open": 97,
        "high": 97.44,
        "low": 96.2,
        "close": 96.67,
        "volume": 189828,
        "qualifyingShares": null,
        "qualifyingDollarVolume": null,
        "qualifyingAvgPrice": null,
        "qualifyingSource": null
      },
      {
        "date": "2026-01-27",
        "open": 96.82,
        "high": 97.82,
        "low": 96.4775,
        "close": 96.89,
        "volume": 130725,
        "qualifyingShares": null,
        "qualifyingDollarVolume": null,
        "qualifyingAvgPrice": null,
        "qualifyingSource": null
      },
      {
        "date": "2026-01-28",
        "open": 97.48,
        "high": 97.53,
        "low": 97.01,
        "close": 97.27,
        "volume": 121425,
        "qualifyingShares": null,
        "qualifyingDollarVolume": null,
        "qualifyingAvgPrice": null,
        "qualifyingSource": null
      },
      {
        "date": "2026-01-29",
        "open": 97.1,
        "high": 97.425,
        "low": 95.5,
        "close": 96.24,
        "volume": 188993,
        "qualifyingShares": null,
        "qualifyingDollarVolume": null,
        "qualifyingAvgPrice": null,
        "qualifyingSource": null
      },
      {
        "date": "2026-01-30",
        "open": 95,
        "high": 95.75,
        "low": 94.5,
        "close": 94.84,
        "volume": 265977,
        "qualifyingShares": null,
        "qualifyingDollarVolume": null,
        "qualifyingAvgPrice": null,
        "qualifyingSource": null
      },
      {
        "date": "2026-02-02",
        "open": 93.65,
        "high": 94.2431,
        "low": 93,
        "close": 93.03,
        "volume": 126258,
        "qualifyingShares": null,
        "qualifyingDollarVolume": null,
        "qualifyingAvgPrice": null,
        "qualifyingSource": null
      },
      {
        "date": "2026-02-03",
        "open": 93.4,
        "high": 93.835,
        "low": 90.53,
        "close": 91.07,
        "volume": 109795,
        "qualifyingShares": null,
        "qualifyingDollarVolume": null,
        "qualifyingAvgPrice": null,
        "qualifyingSource": null
      },
      {
        "date": "2026-02-04",
        "open": 91.68,
        "high": 91.68,
        "low": 90.01,
        "close": 90.08,
        "volume": 124646,
        "qualifyingShares": null,
        "qualifyingDollarVolume": null,
        "qualifyingAvgPrice": null,
        "qualifyingSource": null
      },
      {
        "date": "2026-02-05",
        "open": 89.78,
        "high": 90,
        "low": 81.02,
        "close": 82.5,
        "volume": 235408,
        "qualifyingShares": null,
        "qualifyingDollarVolume": null,
        "qualifyingAvgPrice": null,
        "qualifyingSource": null
      },
      {
        "date": "2026-02-06",
        "open": 84.02,
        "high": 89.16,
        "low": 82.04,
        "close": 88.705,
        "volume": 338419,
        "qualifyingShares": null,
        "qualifyingDollarVolume": null,
        "qualifyingAvgPrice": null,
        "qualifyingSource": null
      },
      {
        "date": "2026-02-09",
        "open": 89,
        "high": 89.2,
        "low": 84.85,
        "close": 85.73,
        "volume": 261299,
        "qualifyingShares": null,
        "qualifyingDollarVolume": null,
        "qualifyingAvgPrice": null,
        "qualifyingSource": null
      },
      {
        "date": "2026-02-10",
        "open": 86.78,
        "high": 90.49,
        "low": 85.81,
        "close": 88,
        "volume": 81498,
        "qualifyingShares": null,
        "qualifyingDollarVolume": null,
        "qualifyingAvgPrice": null,
        "qualifyingSource": null
      },
      {
        "date": "2026-02-11",
        "open": 87.24,
        "high": 89.1999,
        "low": 87,
        "close": 87.75,
        "volume": 72131,
        "qualifyingShares": null,
        "qualifyingDollarVolume": null,
        "qualifyingAvgPrice": null,
        "qualifyingSource": null
      },
      {
        "date": "2026-02-12",
        "open": 88.64,
        "high": 89.98,
        "low": 87.18,
        "close": 89.12,
        "volume": 144491,
        "qualifyingShares": null,
        "qualifyingDollarVolume": null,
        "qualifyingAvgPrice": null,
        "qualifyingSource": null
      },
      {
        "date": "2026-02-13",
        "open": 89.83,
        "high": 92.5,
        "low": 89.21,
        "close": 92.16,
        "volume": 79420,
        "qualifyingShares": null,
        "qualifyingDollarVolume": null,
        "qualifyingAvgPrice": null,
        "qualifyingSource": null
      },
      {
        "date": "2026-02-17",
        "open": 92,
        "high": 93.99,
        "low": 91.801,
        "close": 93.72,
        "volume": 162062,
        "qualifyingShares": null,
        "qualifyingDollarVolume": null,
        "qualifyingAvgPrice": null,
        "qualifyingSource": null
      },
      {
        "date": "2026-02-18",
        "open": 93.6,
        "high": 94.3215,
        "low": 92.06,
        "close": 92.35,
        "volume": 104924,
        "qualifyingShares": null,
        "qualifyingDollarVolume": null,
        "qualifyingAvgPrice": null,
        "qualifyingSource": null
      },
      {
        "date": "2026-02-19",
        "open": 92.74,
        "high": 93.7,
        "low": 91.9,
        "close": 93.16,
        "volume": 85916,
        "qualifyingShares": null,
        "qualifyingDollarVolume": null,
        "qualifyingAvgPrice": null,
        "qualifyingSource": null
      },
      {
        "date": "2026-02-20",
        "open": 93.17,
        "high": 94.42,
        "low": 93,
        "close": 94.41,
        "volume": 55786,
        "qualifyingShares": null,
        "qualifyingDollarVolume": null,
        "qualifyingAvgPrice": null,
        "qualifyingSource": null
      },
      {
        "date": "2026-02-23",
        "open": 94,
        "high": 94.6,
        "low": 93.1,
        "close": 93.31,
        "volume": 112072.297232,
        "qualifyingShares": null,
        "qualifyingDollarVolume": null,
        "qualifyingAvgPrice": null,
        "qualifyingSource": null
      },
      {
        "date": "2026-02-24",
        "open": 93.33,
        "high": 94.41,
        "low": 92.62,
        "close": 93.05,
        "volume": 108403.714932,
        "qualifyingShares": null,
        "qualifyingDollarVolume": null,
        "qualifyingAvgPrice": null,
        "qualifyingSource": null
      },
      {
        "date": "2026-02-25",
        "open": 93.87,
        "high": 95.44,
        "low": 93.795,
        "close": 95.3,
        "volume": 99034.433784,
        "qualifyingShares": null,
        "qualifyingDollarVolume": null,
        "qualifyingAvgPrice": null,
        "qualifyingSource": null
      },
      {
        "date": "2026-02-26",
        "open": 95.55,
        "high": 97.72,
        "low": 94.9,
        "close": 96.39,
        "volume": 336606.287323,
        "qualifyingShares": null,
        "qualifyingDollarVolume": null,
        "qualifyingAvgPrice": null,
        "qualifyingSource": null
      },
      {
        "date": "2026-02-27",
        "open": 95.12,
        "high": 95.5,
        "low": 94,
        "close": 94.81,
        "volume": 161872.932884,
        "qualifyingShares": null,
        "qualifyingDollarVolume": null,
        "qualifyingAvgPrice": null,
        "qualifyingSource": null
      },
      {
        "date": "2026-03-02",
        "open": 94.5,
        "high": 95.5,
        "low": 93.75,
        "close": 94.2,
        "volume": 118501.495086,
        "qualifyingShares": null,
        "qualifyingDollarVolume": null,
        "qualifyingAvgPrice": null,
        "qualifyingSource": null
      },
      {
        "date": "2026-03-03",
        "open": 93.01,
        "high": 94.2499,
        "low": 93,
        "close": 93.5,
        "volume": 30383.618373,
        "qualifyingShares": null,
        "qualifyingDollarVolume": null,
        "qualifyingAvgPrice": null,
        "qualifyingSource": null
      },
      {
        "date": "2026-03-04",
        "open": 94.63,
        "high": 94.64,
        "low": 93.5,
        "close": 94.61,
        "volume": 91218.862401,
        "qualifyingShares": null,
        "qualifyingDollarVolume": null,
        "qualifyingAvgPrice": null,
        "qualifyingSource": null
      },
      {
        "date": "2026-03-05",
        "open": 94,
        "high": 94.96,
        "low": 93.61,
        "close": 94.94,
        "volume": 105070.043766,
        "qualifyingShares": null,
        "qualifyingDollarVolume": null,
        "qualifyingAvgPrice": null,
        "qualifyingSource": null
      },
      {
        "date": "2026-03-06",
        "open": 94.69,
        "high": 95.1599,
        "low": 94.0303,
        "close": 94.57,
        "volume": 38570.201638,
        "qualifyingShares": null,
        "qualifyingDollarVolume": null,
        "qualifyingAvgPrice": null,
        "qualifyingSource": null
      },
      {
        "date": "2026-03-09",
        "open": 94.26,
        "high": 94.92,
        "low": 94,
        "close": 94.78,
        "volume": 50902.747344,
        "qualifyingShares": null,
        "qualifyingDollarVolume": null,
        "qualifyingAvgPrice": null,
        "qualifyingSource": null
      },
      {
        "date": "2026-03-10",
        "open": 94.85,
        "high": 94.92,
        "low": 94.3999,
        "close": 94.85,
        "volume": 82763.386904,
        "qualifyingShares": null,
        "qualifyingDollarVolume": null,
        "qualifyingAvgPrice": null,
        "qualifyingSource": null
      },
      {
        "date": "2026-03-11",
        "open": 95.4,
        "high": 96.44,
        "low": 94.95,
        "close": 95.9997,
        "volume": 353028.369304,
        "qualifyingShares": null,
        "qualifyingDollarVolume": null,
        "qualifyingAvgPrice": null,
        "qualifyingSource": null
      },
      {
        "date": "2026-03-12",
        "open": 96.02,
        "high": 96.02,
        "low": 95.4,
        "close": 95.8,
        "volume": 83410.829658,
        "qualifyingShares": null,
        "qualifyingDollarVolume": null,
        "qualifyingAvgPrice": null,
        "qualifyingSource": null
      },
      {
        "date": "2026-03-13",
        "open": 96.4,
        "high": 96.88,
        "low": 96.105,
        "close": 96.75,
        "volume": 235486.293425,
        "qualifyingShares": null,
        "qualifyingDollarVolume": null,
        "qualifyingAvgPrice": null,
        "qualifyingSource": null
      },
      {
        "date": "2026-03-16",
        "open": 97.08,
        "high": 97.75,
        "low": 97,
        "close": 97.75,
        "volume": 262691.473664,
        "qualifyingShares": null,
        "qualifyingDollarVolume": null,
        "qualifyingAvgPrice": null,
        "qualifyingSource": null
      },
      {
        "date": "2026-03-17",
        "open": 98.01,
        "high": 98.7,
        "low": 98.01,
        "close": 98.7,
        "volume": 206931.280711,
        "qualifyingShares": null,
        "qualifyingDollarVolume": null,
        "qualifyingAvgPrice": null,
        "qualifyingSource": null
      },
      {
        "date": "2026-03-18",
        "open": 98.9,
        "high": 98.9,
        "low": 97.5,
        "close": 97.56,
        "volume": 168265.413701,
        "qualifyingShares": null,
        "qualifyingDollarVolume": null,
        "qualifyingAvgPrice": null,
        "qualifyingSource": null
      },
      {
        "date": "2026-03-19",
        "open": 97.1,
        "high": 98.4899,
        "low": 97.0101,
        "close": 97.76,
        "volume": 103348.080084,
        "qualifyingShares": null,
        "qualifyingDollarVolume": null,
        "qualifyingAvgPrice": null,
        "qualifyingSource": null
      },
      {
        "date": "2026-03-20",
        "open": 98.15,
        "high": 98.15,
        "low": 97.06,
        "close": 97.1,
        "volume": 125200.314673,
        "qualifyingShares": null,
        "qualifyingDollarVolume": null,
        "qualifyingAvgPrice": null,
        "qualifyingSource": null
      },
      {
        "date": "2026-03-23",
        "open": 98.09,
        "high": 98.1,
        "low": 96.885,
        "close": 97.88,
        "volume": 136222.74658,
        "qualifyingShares": null,
        "qualifyingDollarVolume": null,
        "qualifyingAvgPrice": null,
        "qualifyingSource": null
      },
      {
        "date": "2026-03-24",
        "open": 97.9,
        "high": 98.25,
        "low": 97.76,
        "close": 98.25,
        "volume": 131290.017637,
        "qualifyingShares": null,
        "qualifyingDollarVolume": null,
        "qualifyingAvgPrice": null,
        "qualifyingSource": null
      },
      {
        "date": "2026-03-25",
        "open": 98.6,
        "high": 99.75,
        "low": 98.31,
        "close": 99,
        "volume": 164425.659387,
        "qualifyingShares": null,
        "qualifyingDollarVolume": null,
        "qualifyingAvgPrice": null,
        "qualifyingSource": null
      },
      {
        "date": "2026-03-26",
        "open": 99.05,
        "high": 99.25,
        "low": 98.62,
        "close": 99,
        "volume": 163218.89469,
        "qualifyingShares": null,
        "qualifyingDollarVolume": null,
        "qualifyingAvgPrice": null,
        "qualifyingSource": null
      },
      {
        "date": "2026-03-27",
        "open": 99.15,
        "high": 99.2399,
        "low": 98.55,
        "close": 98.56,
        "volume": 155101.085624,
        "qualifyingShares": null,
        "qualifyingDollarVolume": null,
        "qualifyingAvgPrice": null,
        "qualifyingSource": null
      },
      {
        "date": "2026-03-30",
        "open": 99.39,
        "high": 99.87,
        "low": 98.62,
        "close": 99.43,
        "volume": 416837.324145,
        "qualifyingShares": null,
        "qualifyingDollarVolume": null,
        "qualifyingAvgPrice": null,
        "qualifyingSource": null
      },
      {
        "date": "2026-03-31",
        "open": 99.65,
        "high": 100.01,
        "low": 99.42,
        "close": 99.73,
        "volume": 429087.332832,
        "qualifyingShares": 49393.133711,
        "qualifyingDollarVolume": 4939366.58243711,
        "qualifyingAvgPrice": 100.00107730231132,
        "qualifyingSource": "5m"
      },
      {
        "date": "2026-04-01",
        "open": 98.51,
        "high": 98.595,
        "low": 96.5,
        "close": 97.98,
        "volume": 182655.719853,
        "qualifyingShares": null,
        "qualifyingDollarVolume": null,
        "qualifyingAvgPrice": null,
        "qualifyingSource": null
      },
      {
        "date": "2026-04-02",
        "open": 97.87,
        "high": 97.99,
        "low": 97.03,
        "close": 97.27,
        "volume": 86819.578248,
        "qualifyingShares": null,
        "qualifyingDollarVolume": null,
        "qualifyingAvgPrice": null,
        "qualifyingSource": null
      },
      {
        "date": "2026-04-06",
        "open": 97.7,
        "high": 97.85,
        "low": 97.28,
        "close": 97.72,
        "volume": 134833.623429,
        "qualifyingShares": null,
        "qualifyingDollarVolume": null,
        "qualifyingAvgPrice": null,
        "qualifyingSource": null
      },
      {
        "date": "2026-04-07",
        "open": 97.34,
        "high": 97.8,
        "low": 97.34,
        "close": 97.42,
        "volume": 57904.43117,
        "qualifyingShares": null,
        "qualifyingDollarVolume": null,
        "qualifyingAvgPrice": null,
        "qualifyingSource": null
      },
      {
        "date": "2026-04-08",
        "open": 98,
        "high": 98.02,
        "low": 97.55,
        "close": 98.01,
        "volume": 80589.439918,
        "qualifyingShares": null,
        "qualifyingDollarVolume": null,
        "qualifyingAvgPrice": null,
        "qualifyingSource": null
      },
      {
        "date": "2026-04-09",
        "open": 98.06,
        "high": 98.25,
        "low": 97.8601,
        "close": 98.13,
        "volume": 64902.084129,
        "qualifyingShares": null,
        "qualifyingDollarVolume": null,
        "qualifyingAvgPrice": null,
        "qualifyingSource": null
      },
      {
        "date": "2026-04-10",
        "open": 98,
        "high": 98.2987,
        "low": 97.9523,
        "close": 98.21,
        "volume": 60726.900299,
        "qualifyingShares": null,
        "qualifyingDollarVolume": null,
        "qualifyingAvgPrice": null,
        "qualifyingSource": null
      },
      {
        "date": "2026-04-13",
        "open": 98,
        "high": 98.3,
        "low": 97.4,
        "close": 97.5,
        "volume": 171973.001262,
        "qualifyingShares": null,
        "qualifyingDollarVolume": null,
        "qualifyingAvgPrice": null,
        "qualifyingSource": null
      },
      {
        "date": "2026-04-14",
        "open": 97.3,
        "high": 97.978,
        "low": 97.29,
        "close": 97.95,
        "volume": 128663.942316,
        "qualifyingShares": null,
        "qualifyingDollarVolume": null,
        "qualifyingAvgPrice": null,
        "qualifyingSource": null
      },
      {
        "date": "2026-04-15",
        "open": 98.08,
        "high": 99.85,
        "low": 97.7903,
        "close": 99.7,
        "volume": 202095.442267,
        "qualifyingShares": null,
        "qualifyingDollarVolume": null,
        "qualifyingAvgPrice": null,
        "qualifyingSource": null
      },
      {
        "date": "2026-04-16",
        "open": 99.4,
        "high": 99.4,
        "low": 99.05,
        "close": 99.26,
        "volume": 124032.126732,
        "qualifyingShares": null,
        "qualifyingDollarVolume": null,
        "qualifyingAvgPrice": null,
        "qualifyingSource": null
      },
      {
        "date": "2026-04-17",
        "open": 99.4,
        "high": 99.58,
        "low": 99.15,
        "close": 99.58,
        "volume": 193747.943878,
        "qualifyingShares": null,
        "qualifyingDollarVolume": null,
        "qualifyingAvgPrice": null,
        "qualifyingSource": null
      },
      {
        "date": "2026-04-20",
        "open": 99.5,
        "high": 99.65,
        "low": 99.45,
        "close": 99.55,
        "volume": 121253.881131,
        "qualifyingShares": null,
        "qualifyingDollarVolume": null,
        "qualifyingAvgPrice": null,
        "qualifyingSource": null
      },
      {
        "date": "2026-04-21",
        "open": 99.65,
        "high": 99.65,
        "low": 99.43,
        "close": 99.54,
        "volume": 81735.545603,
        "qualifyingShares": null,
        "qualifyingDollarVolume": null,
        "qualifyingAvgPrice": null,
        "qualifyingSource": null
      },
      {
        "date": "2026-04-22",
        "open": 99.6,
        "high": 99.91,
        "low": 99.55,
        "close": 99.91,
        "volume": 293300.680068,
        "qualifyingShares": 100000,
        "qualifyingDollarVolume": 10000000,
        "qualifyingAvgPrice": 100,
        "qualifyingSource": "1m"
      },
      {
        "date": "2026-04-23",
        "open": 99.96,
        "high": 99.97,
        "low": 99.83,
        "close": 99.97,
        "volume": 236223.276098,
        "qualifyingShares": 100001.2665,
        "qualifyingDollarVolume": 10000126.65,
        "qualifyingAvgPrice": 100,
        "qualifyingSource": "1m"
      },
      {
        "date": "2026-04-24",
        "open": 99.99,
        "high": 99.99,
        "low": 99.8,
        "close": 99.86,
        "volume": 94306.779726,
        "qualifyingShares": null,
        "qualifyingDollarVolume": null,
        "qualifyingAvgPrice": null,
        "qualifyingSource": null
      },
      {
        "date": "2026-04-27",
        "open": 99.99,
        "high": 100,
        "low": 99.92,
        "close": 99.99,
        "volume": 157621.980313,
        "qualifyingShares": 10540.4313,
        "qualifyingDollarVolume": 1054043.1300000001,
        "qualifyingAvgPrice": 100.00000000000001,
        "qualifyingSource": "1m"
      }
    ],
    "intraday1m": [
      {
        "t": 1777287600000,
        "o": 99.95,
        "h": 99.96,
        "l": 99.95,
        "c": 99.96,
        "v": 238
      },
      {
        "t": 1777289700000,
        "o": 99.9,
        "h": 99.9,
        "l": 99.9,
        "c": 99.9,
        "v": 301
      },
      {
        "t": 1777292400000,
        "o": 99.92,
        "h": 99.92,
        "l": 99.92,
        "c": 99.92,
        "v": 115
      },
      {
        "t": 1777294080000,
        "o": 99.95,
        "h": 99.95,
        "l": 99.95,
        "c": 99.95,
        "v": 130
      },
      {
        "t": 1777294860000,
        "o": 99.95,
        "h": 99.95,
        "l": 99.95,
        "c": 99.95,
        "v": 200
      },
      {
        "t": 1777295040000,
        "o": 99.95,
        "h": 99.95,
        "l": 99.95,
        "c": 99.95,
        "v": 185
      },
      {
        "t": 1777296300000,
        "o": 99.98,
        "h": 99.99,
        "l": 99.98,
        "c": 99.99,
        "v": 800
      },
      {
        "t": 1777296600000,
        "o": 99.99,
        "h": 99.99,
        "l": 99.97,
        "c": 99.989,
        "v": 12276.310292
      },
      {
        "t": 1777296660000,
        "o": 99.99,
        "h": 99.99,
        "l": 99.97,
        "c": 99.99,
        "v": 1606.002
      },
      {
        "t": 1777296720000,
        "o": 99.99,
        "h": 99.99,
        "l": 99.97,
        "c": 99.9886,
        "v": 2680.567126
      },
      {
        "t": 1777296840000,
        "o": 99.99,
        "h": 99.99,
        "l": 99.96,
        "c": 99.96,
        "v": 1684
      },
      {
        "t": 1777296900000,
        "o": 99.96,
        "h": 99.96,
        "l": 99.95,
        "c": 99.95,
        "v": 1585
      },
      {
        "t": 1777296960000,
        "o": 99.955,
        "h": 99.99,
        "l": 99.955,
        "c": 99.99,
        "v": 824
      },
      {
        "t": 1777297020000,
        "o": 99.94,
        "h": 99.94,
        "l": 99.92,
        "c": 99.92,
        "v": 1629.76362
      },
      {
        "t": 1777297080000,
        "o": 99.95,
        "h": 99.95,
        "l": 99.95,
        "c": 99.95,
        "v": 108.225112
      },
      {
        "t": 1777297200000,
        "o": 99.955,
        "h": 99.955,
        "l": 99.955,
        "c": 99.955,
        "v": 100
      },
      {
        "t": 1777297320000,
        "o": 99.96,
        "h": 99.96,
        "l": 99.96,
        "c": 99.96,
        "v": 210.05
      },
      {
        "t": 1777297620000,
        "o": 99.96,
        "h": 99.99,
        "l": 99.96,
        "c": 99.99,
        "v": 451
      },
      {
        "t": 1777297680000,
        "o": 99.955,
        "h": 99.955,
        "l": 99.955,
        "c": 99.955,
        "v": 110
      },
      {
        "t": 1777298160000,
        "o": 99.9799,
        "h": 99.98,
        "l": 99.9799,
        "c": 99.98,
        "v": 1005
      },
      {
        "t": 1777298220000,
        "o": 99.9701,
        "h": 99.9701,
        "l": 99.9701,
        "c": 99.9701,
        "v": 123.271323
      },
      {
        "t": 1777298280000,
        "o": 99.97,
        "h": 99.97,
        "l": 99.97,
        "c": 99.97,
        "v": 200.02
      },
      {
        "t": 1777298460000,
        "o": 99.99,
        "h": 99.99,
        "l": 99.99,
        "c": 99.99,
        "v": 265
      },
      {
        "t": 1777298580000,
        "o": 99.98,
        "h": 99.99,
        "l": 99.98,
        "c": 99.99,
        "v": 2994.011
      },
      {
        "t": 1777298640000,
        "o": 99.989,
        "h": 99.99,
        "l": 99.989,
        "c": 99.99,
        "v": 360.361
      },
      {
        "t": 1777298700000,
        "o": 99.99,
        "h": 99.99,
        "l": 99.99,
        "c": 99.99,
        "v": 480
      },
      {
        "t": 1777298760000,
        "o": 99.99,
        "h": 99.99,
        "l": 99.99,
        "c": 99.99,
        "v": 328
      },
      {
        "t": 1777298820000,
        "o": 99.98,
        "h": 99.98,
        "l": 99.98,
        "c": 99.98,
        "v": 110
      },
      {
        "t": 1777298880000,
        "o": 99.99,
        "h": 99.99,
        "l": 99.99,
        "c": 99.99,
        "v": 1103
      },
      {
        "t": 1777299060000,
        "o": 99.99,
        "h": 99.99,
        "l": 99.99,
        "c": 99.99,
        "v": 1262
      },
      {
        "t": 1777299120000,
        "o": 99.99,
        "h": 99.99,
        "l": 99.99,
        "c": 99.99,
        "v": 2684
      },
      {
        "t": 1777299360000,
        "o": 99.985,
        "h": 99.985,
        "l": 99.985,
        "c": 99.985,
        "v": 672
      },
      {
        "t": 1777299420000,
        "o": 99.985,
        "h": 99.985,
        "l": 99.985,
        "c": 99.985,
        "v": 173
      },
      {
        "t": 1777299480000,
        "o": 99.99,
        "h": 99.99,
        "l": 99.99,
        "c": 99.99,
        "v": 410.974063
      },
      {
        "t": 1777299780000,
        "o": 99.985,
        "h": 99.985,
        "l": 99.985,
        "c": 99.985,
        "v": 108
      },
      {
        "t": 1777299900000,
        "o": 99.985,
        "h": 99.985,
        "l": 99.985,
        "c": 99.985,
        "v": 504
      },
      {
        "t": 1777299960000,
        "o": 99.99,
        "h": 99.99,
        "l": 99.99,
        "c": 99.99,
        "v": 321.233532
      },
      {
        "t": 1777300020000,
        "o": 99.99,
        "h": 99.99,
        "l": 99.99,
        "c": 99.99,
        "v": 126
      },
      {
        "t": 1777300080000,
        "o": 99.99,
        "h": 99.99,
        "l": 99.99,
        "c": 99.99,
        "v": 1250
      },
      {
        "t": 1777300200000,
        "o": 99.98,
        "h": 99.98,
        "l": 99.98,
        "c": 99.98,
        "v": 2414.4
      },
      {
        "t": 1777300260000,
        "o": 99.99,
        "h": 99.99,
        "l": 99.99,
        "c": 99.99,
        "v": 111
      },
      {
        "t": 1777300560000,
        "o": 99.99,
        "h": 99.99,
        "l": 99.99,
        "c": 99.99,
        "v": 564.033904
      },
      {
        "t": 1777300620000,
        "o": 99.985,
        "h": 99.985,
        "l": 99.985,
        "c": 99.985,
        "v": 300
      },
      {
        "t": 1777300800000,
        "o": 99.982,
        "h": 99.982,
        "l": 99.98,
        "c": 99.98,
        "v": 3300.020002
      },
      {
        "t": 1777301040000,
        "o": 99.985,
        "h": 99.99,
        "l": 99.985,
        "c": 99.9866,
        "v": 600
      },
      {
        "t": 1777301100000,
        "o": 99.985,
        "h": 99.99,
        "l": 99.985,
        "c": 99.99,
        "v": 739
      },
      {
        "t": 1777301160000,
        "o": 99.98,
        "h": 99.98,
        "l": 99.98,
        "c": 99.98,
        "v": 225.0012
      },
      {
        "t": 1777301400000,
        "o": 99.9899,
        "h": 100,
        "l": 99.9875,
        "c": 100,
        "v": 10540.4313
      },
      {
        "t": 1777301520000,
        "o": 99.99,
        "h": 99.99,
        "l": 99.99,
        "c": 99.99,
        "v": 507
      },
      {
        "t": 1777301700000,
        "o": 99.995,
        "h": 99.995,
        "l": 99.995,
        "c": 99.995,
        "v": 110
      },
      {
        "t": 1777301760000,
        "o": 99.9903,
        "h": 99.995,
        "l": 99.9903,
        "c": 99.995,
        "v": 1149.097
      },
      {
        "t": 1777301820000,
        "o": 99.995,
        "h": 99.995,
        "l": 99.99,
        "c": 99.99,
        "v": 1180.1
      },
      {
        "t": 1777302060000,
        "o": 99.985,
        "h": 99.985,
        "l": 99.98,
        "c": 99.98,
        "v": 302
      },
      {
        "t": 1777302240000,
        "o": 99.98,
        "h": 99.98,
        "l": 99.98,
        "c": 99.98,
        "v": 1018.168075
      },
      {
        "t": 1777302420000,
        "o": 99.985,
        "h": 99.985,
        "l": 99.98,
        "c": 99.98,
        "v": 202
      },
      {
        "t": 1777302540000,
        "o": 99.9896,
        "h": 99.9896,
        "l": 99.9896,
        "c": 99.9896,
        "v": 200
      },
      {
        "t": 1777302600000,
        "o": 99.985,
        "h": 99.985,
        "l": 99.9801,
        "c": 99.9801,
        "v": 660
      },
      {
        "t": 1777302720000,
        "o": 99.98,
        "h": 99.98,
        "l": 99.98,
        "c": 99.98,
        "v": 768
      },
      {
        "t": 1777302780000,
        "o": 99.9886,
        "h": 99.9886,
        "l": 99.9886,
        "c": 99.9886,
        "v": 497
      },
      {
        "t": 1777303080000,
        "o": 99.97,
        "h": 99.97,
        "l": 99.97,
        "c": 99.97,
        "v": 500.020002
      },
      {
        "t": 1777303260000,
        "o": 99.96,
        "h": 99.96,
        "l": 99.96,
        "c": 99.96,
        "v": 657
      },
      {
        "t": 1777303320000,
        "o": 99.96,
        "h": 99.96,
        "l": 99.96,
        "c": 99.96,
        "v": 705.28
      },
      {
        "t": 1777303740000,
        "o": 99.975,
        "h": 99.975,
        "l": 99.975,
        "c": 99.975,
        "v": 458.534456
      },
      {
        "t": 1777304100000,
        "o": 99.9899,
        "h": 99.99,
        "l": 99.9899,
        "c": 99.99,
        "v": 200
      },
      {
        "t": 1777304400000,
        "o": 99.99,
        "h": 99.99,
        "l": 99.9899,
        "c": 99.9899,
        "v": 326.25
      },
      {
        "t": 1777304460000,
        "o": 99.9899,
        "h": 99.9899,
        "l": 99.9899,
        "c": 99.9899,
        "v": 111
      },
      {
        "t": 1777304520000,
        "o": 99.99,
        "h": 99.99,
        "l": 99.99,
        "c": 99.99,
        "v": 604.40144
      },
      {
        "t": 1777304580000,
        "o": 99.99,
        "h": 99.99,
        "l": 99.9897,
        "c": 99.9897,
        "v": 2506
      },
      {
        "t": 1777304640000,
        "o": 99.99,
        "h": 99.99,
        "l": 99.9897,
        "c": 99.9897,
        "v": 200
      },
      {
        "t": 1777304820000,
        "o": 99.99,
        "h": 99.99,
        "l": 99.9812,
        "c": 99.9812,
        "v": 900
      },
      {
        "t": 1777304880000,
        "o": 99.98,
        "h": 99.99,
        "l": 99.98,
        "c": 99.99,
        "v": 6377.229
      },
      {
        "t": 1777305060000,
        "o": 99.985,
        "h": 99.985,
        "l": 99.985,
        "c": 99.985,
        "v": 102
      },
      {
        "t": 1777305120000,
        "o": 99.985,
        "h": 99.985,
        "l": 99.98,
        "c": 99.98,
        "v": 602.23
      },
      {
        "t": 1777305480000,
        "o": 99.98,
        "h": 99.98,
        "l": 99.98,
        "c": 99.98,
        "v": 157
      },
      {
        "t": 1777305840000,
        "o": 99.98,
        "h": 99.98,
        "l": 99.98,
        "c": 99.98,
        "v": 407
      },
      {
        "t": 1777305960000,
        "o": 99.98,
        "h": 99.98,
        "l": 99.975,
        "c": 99.98,
        "v": 566
      },
      {
        "t": 1777306140000,
        "o": 99.985,
        "h": 99.985,
        "l": 99.98,
        "c": 99.98,
        "v": 1109
      },
      {
        "t": 1777306200000,
        "o": 99.98,
        "h": 99.98,
        "l": 99.98,
        "c": 99.98,
        "v": 229
      },
      {
        "t": 1777306260000,
        "o": 99.982,
        "h": 99.982,
        "l": 99.982,
        "c": 99.982,
        "v": 141.12
      },
      {
        "t": 1777306320000,
        "o": 99.9859,
        "h": 99.9859,
        "l": 99.9859,
        "c": 99.9859,
        "v": 351
      },
      {
        "t": 1777306440000,
        "o": 99.99,
        "h": 99.99,
        "l": 99.986,
        "c": 99.99,
        "v": 980
      },
      {
        "t": 1777306560000,
        "o": 99.99,
        "h": 99.99,
        "l": 99.99,
        "c": 99.99,
        "v": 300
      },
      {
        "t": 1777306620000,
        "o": 99.985,
        "h": 99.985,
        "l": 99.985,
        "c": 99.985,
        "v": 593
      },
      {
        "t": 1777306740000,
        "o": 99.99,
        "h": 99.99,
        "l": 99.9899,
        "c": 99.9899,
        "v": 418
      },
      {
        "t": 1777306800000,
        "o": 99.99,
        "h": 99.99,
        "l": 99.9866,
        "c": 99.9866,
        "v": 252
      },
      {
        "t": 1777307100000,
        "o": 99.99,
        "h": 99.99,
        "l": 99.99,
        "c": 99.99,
        "v": 100
      },
      {
        "t": 1777307220000,
        "o": 99.99,
        "h": 99.99,
        "l": 99.99,
        "c": 99.99,
        "v": 187
      },
      {
        "t": 1777307880000,
        "o": 99.985,
        "h": 99.985,
        "l": 99.985,
        "c": 99.985,
        "v": 203
      },
      {
        "t": 1777308060000,
        "o": 99.99,
        "h": 99.99,
        "l": 99.99,
        "c": 99.99,
        "v": 881.088008
      },
      {
        "t": 1777308300000,
        "o": 99.985,
        "h": 99.99,
        "l": 99.9802,
        "c": 99.99,
        "v": 883.49
      },
      {
        "t": 1777308600000,
        "o": 99.99,
        "h": 99.99,
        "l": 99.99,
        "c": 99.99,
        "v": 100
      },
      {
        "t": 1777308900000,
        "o": 99.99,
        "h": 99.99,
        "l": 99.99,
        "c": 99.99,
        "v": 109
      },
      {
        "t": 1777309380000,
        "o": 99.988,
        "h": 99.99,
        "l": 99.988,
        "c": 99.9897,
        "v": 800
      },
      {
        "t": 1777309500000,
        "o": 99.99,
        "h": 99.99,
        "l": 99.99,
        "c": 99.99,
        "v": 100
      },
      {
        "t": 1777309560000,
        "o": 99.99,
        "h": 99.99,
        "l": 99.9897,
        "c": 99.9897,
        "v": 1002
      },
      {
        "t": 1777309620000,
        "o": 99.985,
        "h": 99.985,
        "l": 99.985,
        "c": 99.985,
        "v": 700
      },
      {
        "t": 1777309680000,
        "o": 99.99,
        "h": 99.99,
        "l": 99.99,
        "c": 99.99,
        "v": 988.15
      },
      {
        "t": 1777309860000,
        "o": 99.99,
        "h": 99.99,
        "l": 99.99,
        "c": 99.99,
        "v": 1240.005
      },
      {
        "t": 1777309980000,
        "o": 99.988,
        "h": 99.99,
        "l": 99.988,
        "c": 99.99,
        "v": 603
      },
      {
        "t": 1777310280000,
        "o": 99.9818,
        "h": 99.9818,
        "l": 99.9818,
        "c": 99.9818,
        "v": 250
      },
      {
        "t": 1777310340000,
        "o": 99.99,
        "h": 99.99,
        "l": 99.99,
        "c": 99.99,
        "v": 500
      },
      {
        "t": 1777310460000,
        "o": 99.985,
        "h": 99.985,
        "l": 99.98,
        "c": 99.98,
        "v": 801.011
      },
      {
        "t": 1777310520000,
        "o": 99.9899,
        "h": 99.9899,
        "l": 99.9899,
        "c": 99.9899,
        "v": 500
      },
      {
        "t": 1777310580000,
        "o": 99.99,
        "h": 99.99,
        "l": 99.99,
        "c": 99.99,
        "v": 237
      },
      {
        "t": 1777310700000,
        "o": 99.99,
        "h": 99.99,
        "l": 99.99,
        "c": 99.99,
        "v": 2006.632988
      },
      {
        "t": 1777310760000,
        "o": 99.99,
        "h": 99.99,
        "l": 99.9897,
        "c": 99.99,
        "v": 1128
      },
      {
        "t": 1777310880000,
        "o": 99.985,
        "h": 99.9899,
        "l": 99.98,
        "c": 99.9899,
        "v": 1317
      },
      {
        "t": 1777311480000,
        "o": 99.99,
        "h": 99.99,
        "l": 99.99,
        "c": 99.99,
        "v": 109
      },
      {
        "t": 1777311600000,
        "o": 99.98,
        "h": 99.985,
        "l": 99.98,
        "c": 99.985,
        "v": 540
      },
      {
        "t": 1777311660000,
        "o": 99.98,
        "h": 99.98,
        "l": 99.98,
        "c": 99.98,
        "v": 205
      },
      {
        "t": 1777311960000,
        "o": 99.98,
        "h": 99.98,
        "l": 99.98,
        "c": 99.98,
        "v": 217
      },
      {
        "t": 1777312500000,
        "o": 99.985,
        "h": 99.9898,
        "l": 99.985,
        "c": 99.9898,
        "v": 731
      },
      {
        "t": 1777312620000,
        "o": 99.98,
        "h": 99.99,
        "l": 99.98,
        "c": 99.99,
        "v": 5736
      },
      {
        "t": 1777312800000,
        "o": 99.985,
        "h": 99.985,
        "l": 99.985,
        "c": 99.985,
        "v": 103.51
      },
      {
        "t": 1777313280000,
        "o": 99.985,
        "h": 99.985,
        "l": 99.98,
        "c": 99.98,
        "v": 2004
      },
      {
        "t": 1777313340000,
        "o": 99.985,
        "h": 99.985,
        "l": 99.98,
        "c": 99.985,
        "v": 2110
      },
      {
        "t": 1777313640000,
        "o": 99.99,
        "h": 99.99,
        "l": 99.99,
        "c": 99.99,
        "v": 750
      },
      {
        "t": 1777314120000,
        "o": 99.99,
        "h": 99.99,
        "l": 99.9899,
        "c": 99.9899,
        "v": 200
      },
      {
        "t": 1777314240000,
        "o": 99.99,
        "h": 99.99,
        "l": 99.99,
        "c": 99.99,
        "v": 5000
      },
      {
        "t": 1777314900000,
        "o": 99.99,
        "h": 99.99,
        "l": 99.9899,
        "c": 99.9899,
        "v": 205
      },
      {
        "t": 1777315080000,
        "o": 99.99,
        "h": 99.99,
        "l": 99.99,
        "c": 99.99,
        "v": 2710.025002
      },
      {
        "t": 1777315560000,
        "o": 99.985,
        "h": 99.985,
        "l": 99.985,
        "c": 99.985,
        "v": 250
      },
      {
        "t": 1777316160000,
        "o": 99.985,
        "h": 99.985,
        "l": 99.985,
        "c": 99.985,
        "v": 250
      },
      {
        "t": 1777316280000,
        "o": 99.985,
        "h": 99.985,
        "l": 99.985,
        "c": 99.985,
        "v": 200
      },
      {
        "t": 1777316400000,
        "o": 99.99,
        "h": 99.99,
        "l": 99.99,
        "c": 99.99,
        "v": 2394
      },
      {
        "t": 1777316580000,
        "o": 99.99,
        "h": 99.99,
        "l": 99.99,
        "c": 99.99,
        "v": 114
      },
      {
        "t": 1777316640000,
        "o": 99.985,
        "h": 99.985,
        "l": 99.95,
        "c": 99.95,
        "v": 10127.023102
      },
      {
        "t": 1777316760000,
        "o": 99.975,
        "h": 99.975,
        "l": 99.96,
        "c": 99.975,
        "v": 3150.0184
      },
      {
        "t": 1777317000000,
        "o": 99.99,
        "h": 99.99,
        "l": 99.975,
        "c": 99.975,
        "v": 2352.0436
      },
      {
        "t": 1777317180000,
        "o": 99.975,
        "h": 99.975,
        "l": 99.975,
        "c": 99.975,
        "v": 100
      },
      {
        "t": 1777317240000,
        "o": 99.99,
        "h": 99.99,
        "l": 99.99,
        "c": 99.99,
        "v": 110
      },
      {
        "t": 1777317600000,
        "o": 99.975,
        "h": 99.99,
        "l": 99.975,
        "c": 99.99,
        "v": 339
      },
      {
        "t": 1777317900000,
        "o": 99.985,
        "h": 99.99,
        "l": 99.985,
        "c": 99.99,
        "v": 343
      },
      {
        "t": 1777318020000,
        "o": 99.985,
        "h": 99.99,
        "l": 99.985,
        "c": 99.99,
        "v": 503
      },
      {
        "t": 1777318080000,
        "o": 99.99,
        "h": 99.99,
        "l": 99.99,
        "c": 99.99,
        "v": 292
      },
      {
        "t": 1777318140000,
        "o": 99.985,
        "h": 99.985,
        "l": 99.985,
        "c": 99.985,
        "v": 200
      },
      {
        "t": 1777318200000,
        "o": 99.985,
        "h": 99.985,
        "l": 99.985,
        "c": 99.985,
        "v": 100
      },
      {
        "t": 1777318380000,
        "o": 99.985,
        "h": 99.985,
        "l": 99.985,
        "c": 99.985,
        "v": 100
      },
      {
        "t": 1777318500000,
        "o": 99.9814,
        "h": 99.982,
        "l": 99.9814,
        "c": 99.982,
        "v": 1400
      },
      {
        "t": 1777318560000,
        "o": 99.98,
        "h": 99.98,
        "l": 99.98,
        "c": 99.98,
        "v": 225
      },
      {
        "t": 1777318620000,
        "o": 99.985,
        "h": 99.985,
        "l": 99.985,
        "c": 99.985,
        "v": 105.620562
      },
      {
        "t": 1777318680000,
        "o": 99.985,
        "h": 99.985,
        "l": 99.985,
        "c": 99.985,
        "v": 570
      },
      {
        "t": 1777318740000,
        "o": 99.99,
        "h": 99.99,
        "l": 99.99,
        "c": 99.99,
        "v": 146
      },
      {
        "t": 1777318860000,
        "o": 99.985,
        "h": 99.985,
        "l": 99.98,
        "c": 99.98,
        "v": 1241
      },
      {
        "t": 1777318920000,
        "o": 99.98,
        "h": 99.98,
        "l": 99.98,
        "c": 99.98,
        "v": 118.5001
      },
      {
        "t": 1777319160000,
        "o": 99.99,
        "h": 99.99,
        "l": 99.972,
        "c": 99.974,
        "v": 473
      },
      {
        "t": 1777319220000,
        "o": 99.972,
        "h": 99.974,
        "l": 99.9705,
        "c": 99.974,
        "v": 400
      },
      {
        "t": 1777319340000,
        "o": 99.97,
        "h": 99.97,
        "l": 99.97,
        "c": 99.97,
        "v": 220
      },
      {
        "t": 1777319520000,
        "o": 99.99,
        "h": 99.99,
        "l": 99.99,
        "c": 99.99,
        "v": 151
      },
      {
        "t": 1777319580000,
        "o": 99.985,
        "h": 99.985,
        "l": 99.985,
        "c": 99.985,
        "v": 440
      },
      {
        "t": 1777319640000,
        "o": 99.99,
        "h": 99.99,
        "l": 99.99,
        "c": 99.99,
        "v": 465
      },
      {
        "t": 1777319940000,
        "o": 99.989,
        "h": 99.99,
        "l": 99.98,
        "c": 99.99,
        "v": 840
      },
      {
        "t": 1777321200000,
        "o": 99.98,
        "h": 99.98,
        "l": 99.98,
        "c": 99.98,
        "v": 249
      },
      {
        "t": 1777321740000,
        "o": 99.99,
        "h": 99.99,
        "l": 99.99,
        "c": 99.99,
        "v": 750
      },
      {
        "t": 1777322220000,
        "o": 99.989,
        "h": 99.989,
        "l": 99.989,
        "c": 99.989,
        "v": 100
      },
      {
        "t": 1777323300000,
        "o": 99.99,
        "h": 99.99,
        "l": 99.99,
        "c": 99.99,
        "v": 1512
      },
      {
        "t": 1777329780000,
        "o": 99.99,
        "h": 99.99,
        "l": 99.99,
        "c": 99.99,
        "v": 1375
      }
    ],
    "intradayGranularity": "1m"
  }
}